euskadi.py
euskadi_holidays-0.2.0.dist-info/licenses/LICENSE
euskadi_holidays-0.2.0.dist-info/METADATA
euskadi_holidays-0.2.0.dist-info/WHEEL
euskadi_holidays-0.2.0.dist-info/top_level.txt
euskadi_holidays-0.2.0.dist-info/RECORD
