Metadata-Version: 2.4
Name: euskadi-holidays
Version: 0.2.0
Summary: Librería para obtener festivos de Euskadi desde Open Data Euskadi
Author-email: Diego Piedra <diego@dieveloper.com>
License: MIT
Project-URL: Homepage, https://github.com/GOe-Tech-Center/EuskadiHolidays.git
Requires-Python: >=3.7
License-File: LICENSE
Requires-Dist: requests
Dynamic: license-file
